{
 "absolute_value": 0,
 "align_labels_right": 0,
 "creation": "2025-10-15 12:44:34.886899",
 "custom_format": 1,
 "default_print_language": "en",
 "disabled": 0,
 "doc_type": "Sales Invoice",
 "docstatus": 0,
 "doctype": "Print Format",
 "font_size": 14,
 "html": "{% set child_table_data = doc.items %}\n\n{% set result_list = [] %}\n\n{% for row in child_table_data %}\n    {% set row_dict = {\n        'item_code': row.item_name,\n        'custom_item_range_name': row.custom_item_range_name,\n        'qty': row.qty,\n        'stock_qty': row.stock_qty,\n        'conversion_factor': row.conversion_factor,\n        'uom': row.stock_uom,\n        'rate': row.stock_uom_rate,\n        'amount': row.amount\n    } %}\n    {% set _ = result_list.append(row_dict) %}\n{% endfor %}\n\n{% set sorted_result_list = result_list | sort(attribute='item_code') %}\n\n{% for row in sorted_result_list %}\n    {% set _ = row.update({'idx': loop.index}) %}\n{% endfor %}\n\n<style>\n@media print {\n  @page {\n    size: A4;\n    margin: 10mm 8mm 10mm 8mm !important;\n  }\n  body {\n    font-family: \"Arial\", sans-serif;\n    font-size: 9.5px;\n    -webkit-print-color-adjust: exact !important;\n    color-adjust: exact !important;\n    line-height: 1.2;\n  }\n  table {\n    border-collapse: collapse;\n    width: 100%;\n    table-layout: fixed;\n    word-wrap: break-word;\n  }\n  th, td {\n    padding: 2px 3px;\n    word-break: break-word;\n    vertical-align: top;\n  }\n  img {\n    max-width: 100%;\n  }\n  .content-01, .content-02 {\n    page-break-inside: avoid;\n  }\n}\n\n/* for PDF generation consistency */\ntable {\n  border-collapse: collapse !important;\n  width: 100% !important;\n  table-layout: fixed !important;\n  word-wrap: break-word !important;\n}\nth, td {\n  font-size: 9px !important;\n  word-break: break-word !important;\n  white-space: normal !important;\n  line-height: 1.2 !important;\n  padding: 2px 4px !important;\n}\n.content-01 {\n  font-size: 9.5px !important;\n}\n</style>\n\n<div style=\"font-size:12px;\" class=\"content-01\">\n    <table border=\"1\" style=\"border-top: 8px inset black; border-bottom: 8px outset black; border-left: none; border-right: none;\" width=\"100%\">\n    <tbody><tr>\n        <!--<td style=\"border-right: 2px solid grey;\" width=\"30%\"><div style=\"padding-top: 10px; padding-left: 20px;\"><img alt=\"logo\" height=\"\" src=\"/files/1519915234882.jpg\" style=\"height: 80px; width: 140px; filter: grayscale(100%);\"></div></td>-->\n        <td style=\"border-right: 2px solid grey;\" width=\"30%\"><div style=\"padding-top: 5px; padding-left: 75px;\"><img alt=\"logo\" height=\"\" src=\"/files/shree logo.jpg\" style=\"height: 100px; width: 100px; filter: grayscale(100%);\"></div></td>\n        <td>\n            <div style=\"display: inline;\">\n                <div style=\"font-family: cursive; font-size: 16px; font-weight: bold;\"><img alt=\"name1\" src=\"/files/Name.png\" style=\"height: 30px; width: 250px; filter: grayscale(100%); padding-left: 50px;\"><u>Rakhi Pvt. Ltd.</u></div>\n                <p style=\"padding-left: 50px; font-size: 10px;\">P- 31A Kalakar Street, 3rd Floor, Kolkata - 700007 <br>Phone 2270 1893/94, M.9331150473 <br>WAREHOUSE : 89/1, Salkia School Road, Howrah-711106 <br>Phone : 2665-4107 E-mail : shreerakhi@gmail.com <br>GSTIN : 19AAECM5102C1ZY CIN NO - U74999WB2005PTC104002</p>\n            </div>\n        </td>\n    </tr>\n    </tbody>\n    </table>\n    <table width=\"100%\" class=\"table table-bordered\">\n        \n    {%- if doc.is_return -%}\n        <tr>\n            <td colspan=\"3\" align=\"center\"><b>Credit Note</b></td>\n        </tr>\n    {%- else -%}\n        {%- if doc.meta.is_submittable and doc.docstatus==0-%}\n            <tr>\n                <td colspan=\"3\" align=\"center\"><b>Proforma Invoice</b></td>\n            </tr>\n        {%- else -%}\n            <tr>\n                <td colspan=\"3\" align=\"center\"><b>BILL OF SUPPLY</b></td>\n            </tr>\n        {%- endif -%}\n    {%- endif -%}\n        <tr>\n            <td width=\"53%\">INVOICE NO. : {{doc.name}}&emsp;&emsp;&emsp;&emsp;&emsp;DATE : {{doc.get_formatted('posting_date')}}</td>\n            <td width=\"47%\" colspan=\"2\"><b>State Code & Name :</b>&emsp;{{doc.place_of_supply}}<div style=\"right:5px; display:inline-block;position:absolute;\">Page No : 1</div></td>\n        </tr>\n        <tr>\n            {% if doc.shipping_address_name and doc.shipping_address %}\n            <td width=\"50%\"><b>Billing Address :</b><br><b>{{doc.customer_name}}<br>{{ doc.address_display|replace('<br>', ' ') }}<br><br>Shipping Address :</b><br><b>{{doc.shipping_address_name}}<br>{{ doc.shipping_address|replace('<br>', ' ') }}</b></td>\n            {% else %}\n            <td width=\"50%\"><b>Billing Address :</b><br><b>{{doc.customer_name}}<br>{{ doc.address_display|replace('<br>', ' ') }}<br><br><br></b></td>\n            {% endif %}\n            {% if doc.custom_lr_number %}\n            <td width=\"20%\" style=\"border-right:0;\"><b>Client's Phone No.</b><br><b>GSTIN</b><br><b>BOS Transporter</b><br><b>LR Number<br></b><b>PRODUCT DESCRIPTION</b></td>\n            <td width=\"30%\" style=\"border-left:0;\">MB-{{ doc.contact_mobile }}<br>{{ doc.billing_address_gstin }}<br>{{ doc.custom_bos_transporter }}<br>{{ doc.custom_lr_number }}<br>EXEMPTED</td>\n            {% else %}\n            <td width=\"20%\" style=\"border-right:0;\"><b>Client's Phone No.</b><br><b>GSTIN</b><br><b>BOS Transporter</b><br><br><b>PRODUCT DESCRIPTION</b></td>\n            <td width=\"30%\" style=\"border-left:0;\">MB-{{ doc.contact_mobile }}<br>{{ doc.billing_address_gstin }}<br>{{ doc.custom_bos_transporter }}<br>EXEMPTED</td>\n            {% endif %}\n        </tr>\n    </table>\n    <table width=\"100%\" class=\"table table-bordered\" border=\"1\" style=\"margin-top:-21px\">\n        <tr align=\"center\">\n            <th width=\"7%\">SL.NO</th>\n            <th width=\"23%\" align=\"left\" colspan=2>ITEM NO</th>\n            <!-- <td width=\"16%\" align=\"left\">ITEM RANGE</td> -->\n            <th width=\"10%\" align=\"right\">BOX</th>\n            <th width=\"10%\" align=\"right\">PACKING</th>\n            <th width=\"10%\" align=\"center\">UNIT</th>\n            <th width=\"10%\" align=\"right\">QUANTITY</th>\n            <th width=\"10%\" align=\"right\">RATE</th>\n            <th width=\"20%\" align=\"right\">AMOUNT</th>\n        </tr>\n        <tr>\n            <td colspan=\"9\"><br></td>\n        </tr>\n        {% set vars = {'total_box':0.0,'total_amount': 0.0, 'last_idx':0} %}\n        {% set item_len = sorted_result_list|length %}\n        {% for item in sorted_result_list %}\n            {% if item['idx'] <= 25 %}\n                <tr>\n                    <td width=\"7%\" align=\"center\" colspan=2>{{ item['idx'] }}</td>\n                    <td width=\"23%\">{{ item['item_code'] }}</td>\n                  <!--  <td width=\"16%\">{{ item['custom_item_range_name'] }}</td> -->\n                    <td width=\"10%\" align=\"right\">{{ item['qty']|int }}</td>\n                    <td width=\"10%\" align=\"right\">{{ \"%0.2f\" | format(item['conversion_factor']|float) }}</td>\n                    <td width=\"10%\" align=\"center\">{{ item['uom'] }}</td>\n                    <td width=\"10%\" align=\"right\">{{ \"%0.2f\" | format(item['stock_qty']|float) }}</td>\n                    <td width=\"10%\" align=\"right\">{{ \"%0.2f\" | format(item['rate']|float) }}</td>\n                    <td width=\"20%\"align=\"right\">{{ \"%0.2f\" | format(item['amount']|float) }}</td>\n                    \n                    {% set vars = vars.update({'total_box': vars.total_box + item['qty']|int, 'total_amount': vars.total_amount + item['amount']|float,\n                    'last_idx': vars.last_idx + 1}) %}\n                </tr>\n            {% endif %}\n        {% endfor %}\n        {% if item_len > 25 %}\n        <tr>\n            <td colspan=\"9\"><br></td>\n        </tr>\n        <tr>\n            <td></td>\n            <td colspan=2></td>\n            <!-- <td></td> -->\n            <td align=\"right\" style=\"font-weight:bold;\">{{ vars.total_box|int }}</td>\n            <td></td>\n            <td></td>\n            <td></td>\n            <td></td>\n            <td align=\"right\" style=\"font-weight:bold;\">{{ \"%0.2f\" | format(vars.total_amount|round(2)) }}</td>\n        </tr>\n        {% endif %}\n        {% if vars.last_idx == item_len  %}\n        <tr>\n            <td colspan=\"9\"><br></td>\n        </tr>\n        <tr>\n            <td></td>\n            <td style=\"border-right:0;\" align=\"left\" colspan=2><b><i>AMOUNT</i></b></td>\n            <!--<td style=\"border-right:0; border-left:0;\"></td> -->\n            <td style=\"border-left:0;\" align=\"right\"><b>{{ vars.total_box|int }}</b></td>\n            <td colspan=\"3\"></td>\n            <td align=\"right\"></td>\n            <td align=\"right\"><b>{{ \"%0.2f\" | format(vars.total_amount|round(2)) }}</b></td>\n        </tr>\n        <tr>\n            <td></td>\n            <td colspan=\"6\">DISCOUNT</td>\n            <td align=\"right\">{{ \"%0.2f\" | format( doc.additional_discount_percentage|float) }}%</td>\n            <td align=\"right\">- {{ \"%0.2f\" | format(doc.discount_amount|float) }}</td>\n        </tr>\n        {% for row in doc.taxes %}\n        <tr>\n            {% if row.description != 'Freight and Forwarding Charges' %}\n            <td></td>\n            <td colspan=\"6\">{{ row.description }}</td>\n            <td></td>\n            <td align=\"right\">{{ \"%0.2f\" | format(row.tax_amount|float) }}</td>\n            {% else %}\n            <td></td>\n            <td colspan=\"3\" style=\"border-right:0;\">{{ row.description }}</td>\n            <td colspan=\"2\" style=\"border-left:0; border-right-color:transparent;\">No. of cases</td>\n            <td align=\"right\" style=\"border-left:0;\">{{ \"%0.2f\" | format(doc.custom_number_of_carton|float) }}</td>\n            <td align=\"right\">{{ \"%0.2f\" | format(doc.custom_rate_per_carton|float) }}</td>\n            <td align=\"right\">{{ \"%0.2f\" | format(row.tax_amount|float) }}</td>\n            {% endif %}\n        </tr>\n        {% endfor %}\n        <tr>\n            <td></td>\n            <td colspan=\"6\" style=\"font-weight:bold\"><i>TOTAL AMOUNT</i></td>\n            <td></td>\n            <td align=\"right\"><b>{{ \"%0.2f\" | format(doc.rounded_total|float) }}</b></td>\n        </tr>\n        <tr>\n            <td colspan=\"9\"><i>Rs. {{ doc.in_words[4:] }}</i></td>\n        </tr>\n    </table>\n    <table border=1 width=\"100%\" class=\"table table-bordered\" style=\"margin-top:-21px\">\n        <tbody>\n            <tr>\n                <td>{{ doc.other_charges_calculation }}</td>\n\n            </tr>\n        </tbody>\n    </table>\n    <table width=\"100%\" style=\"margin-top:-21px; font-weight:bold\">\n        <tr>\n            <td>\n                <p>Please pay in favour of \"M.D.MOHTA RAKHI PVT.LTD.\" Through either</p>\n                <p>ICICI Bank Ltd.,Kolkata A/c No 694905600912 IFSC Code ICIC0006949 or</p>\n                <p>DBS Bank India Limited A/c No 828200135528 IFSC Code DBSS0IN0828</p>\n                <p>Rakhi is exempted from GST vide Notification No.19/2018 Dated 26/07/18</p>\n            </td>\n            <td style=\"text-align:center;\">Authorised Signatory</td>\n        </tr>\n        <tr>\n            <td><p>Amendment No.02/2017 Dated 28/06/2017</p></td>\n            <td style=\"text-align:center;\">E.& O.E.</td>\n        </tr>\n    </table>\n    {% endif %}\n</div>\n\n\n\n\n{% if item_len > 25 %}\n<div style=\"font-size:12px;\" class=\"content-02\">\n    {% set total_page = (item_len - 25)/35 %}\n    {% if total_page|int == total_page|float %}\n    {% set total_page = total_page|int + 0 %}\n    {% else %}\n    {% set total_page = total_page|int + 1 %}\n    {% endif %}\n    {% for i in range(1, total_page|int + 1) %}\n    <table width=\"100%\" class=\"table table-bordered\" style=\"page-break-before: always;\">\n        <tr>\n            <td colspan=\"2\" align=\"center\"><b>BILL OF SUPPLY</b></td>\n        </tr>\n        <tr>\n            <td width=\"51.6%\">INVOICE NO. : {{doc.name}}&emsp;&emsp;&emsp;&emsp;&emsp;DATE : {{doc.get_formatted('posting_date')}}</td>\n            <td width=\"48.4%\"><b>State Code & Name :</b>&emsp;{{doc.place_of_supply}}<div style=\"right:5px; display:inline-block;position:absolute;\">Page No : {{ i + 1 }}</div></td>\n        </tr>\n    </table>\n    <table width=\"100%\" class=\"table table-bordered\" style=\"margin-top:-21px;\">\n        <tr align=\"center\">\n            <th width=\"7%\">SL.NO</th>\n            <th width=\"23%\" align=\"left\" colspan=2>ITEM NO</th>\n            <!-- <td width=\"16%\" align=\"left\">ITEM RANGE</td> -->\n            <th width=\"10%\" align=\"right\">BOX</th>\n            <th width=\"10%\" align=\"right\">PACKING</th>\n            <th width=\"10%\" align=\"center\">UNIT</th>\n            <th width=\"10%\" align=\"right\">QUANTITY</th>\n            <th width=\"10%\" align=\"right\">RATE</th>\n            <th width=\"20%\" align=\"right\">AMOUNT</th>\n        </tr>\n        <tr>\n            <td colspan=\"9\"><br></td>\n        </tr>\n                <tr>\n                    <td></td>\n                    <td colspan=2></td>\n                    <!-- <td></td> -->\n                    <td align=\"right\" style=\"font-weight:bold;\">{{ vars.total_box|int }}</td>\n                    <td></td>\n                    <td align=\"right\"></td>\n                    <td align=\"center\"></td>\n                    <td align=\"right\"></td>\n                    <td align=\"right\" style=\"font-weight:bold;\">{{ \"%0.2f\" | format(vars.total_amount|round(2)) }}</td>\n                </tr>\n        {% set vars1 = {'last_idx_1': vars.last_idx + 35} %}\n        {% for item in sorted_result_list %}\n            {% if item['idx'] > vars.last_idx and item['idx'] <= vars1.last_idx_1 %}\n                <tr>\n                    <td align=\"center\">{{ item['idx'] }}</td>\n                    <td width=\"26%\" colspan=2>{{ item['item_code'] }}</td>\n                  <!--  <td width=\"16%\">{{ item['custom_item_range_name'] }}</td>-->\n                    <td align=\"right\">{{ item['qty']|int }}</td>\n                    <td align=\"right\">{{ \"%0.2f\" | format(item['conversion_factor']|float) }}</td>\n                    <td align=\"center\">{{ item['uom'] }}</td>\n                    <td align=\"right\">{{ \"%0.2f\" | format(item['stock_qty']|float) }}</td>\n                    <td align=\"right\">{{ \"%0.2f\" | format(item['rate']|float) }}</td>\n                    <td align=\"right\">{{ \"%0.2f\" | format(item['amount']|float) }}</td>\n                    {% set vars = vars.update({'total_box': vars.total_box + item['qty']|int, 'total_amount': vars.total_amount + item['amount']|float,\n                    'last_idx': vars.last_idx + 1}) %}\n                </tr>\n            {% endif %}\n        {% endfor %}\n        {% if vars.last_idx != item_len  %}\n        <tr>\n            <td colspan=\"9\"><br></td>\n        </tr>\n        <tr>\n            <td></td>\n            <td colspan=2></td>\n            <!-- <td></td> -->\n            <td align=\"right\" style=\"font-weight:bold;\">{{ vars.total_box|int }}</td>\n            <td></td>\n            <td align=\"right\"></td>\n            <td align=\"center\"></td>\n            <td align=\"right\"></td>\n            <td align=\"right\" style=\"font-weight:bold;\">{{ \"%0.2f\" | format(vars.total_amount|round(2)) }}</td>\n        </tr>\n        {% endif %}\n        {% if vars.last_idx == item_len  %}\n        <tr>\n            <td colspan=\"9\"><br></td>\n        </tr>\n        <tr>\n            <td></td>\n            <td style=\"border-right:0;\" align=\"left\"><b><i>AMOUNT</i></b></td>\n            <td style=\"border-right:0; border-left:0;\"></td>\n            <td style=\"border-left:0;\" align=\"right\"><b>{{ vars.total_box|int }}</b></td>\n            <td colspan=\"3\"></td>\n            <td align=\"right\"></td>\n            <td align=\"right\"><b>{{ \"%0.2f\" | format(vars.total_amount|round(2)) }}</b></td>\n        </tr>\n\n        <tr>\n            <td></td>\n            <td colspan=\"6\">DISCOUNT</td>\n            <td align=\"right\">{{ \"%0.2f\" | format( doc.additional_discount_percentage|float) }}%</td>\n            <td align=\"right\">- {{ \"%0.2f\" | format(doc.discount_amount|float) }}</td>\n        </tr>\n        {% for row in doc.taxes %}\n        <tr>\n            {% if row.description != 'Freight and Forwarding Charges' %}\n            <td></td>\n            <td colspan=\"6\">{{ row.description }}</td>\n            <td></td>\n            <td align=\"right\">{{ \"%0.2f\" | format(row.tax_amount|float) }}</td>\n            {% else %}\n            <td></td>\n            <td colspan=\"3\" style=\"border-right:0;\">{{ row.description }}</td>\n            <td colspan=\"2\" style=\"border-left:0; border-right-color:transparent;\">No. of cases</td>\n            <td align=\"right\" style=\"border-left:0;\">{{ \"%0.2f\" | format(doc.custom_number_of_carton|float) }}</td>\n            <td align=\"right\">{{ \"%0.2f\" | format(doc.custom_rate_per_carton|float) }}</td>\n            <td align=\"right\">{{ \"%0.2f\" | format(row.tax_amount|float) }}</td>\n            {% endif %}\n        </tr>\n        {% endfor %}\n        <tr>\n            <td></td>\n            <td colspan=\"6\" style=\"font-weight:bold\"><i>TOTAL AMOUNT</i></td>\n            <td></td>\n            <td align=\"right\"><b>{{ \"%0.2f\" | format(doc.rounded_total|float) }}</b></td>\n        </tr>\n        <tr>\n            <td colspan=\"9\"><i>Rs. {{ doc.in_words[4:] }}</i></td>\n        </tr>\n    </table>\n    <table border=1 width=\"100%\" class=\"table table-bordered\" style=\"margin-top:-21px\">\n        <tbody>\n            <tr>\n                <td>{{ doc.other_charges_calculation }}</td>\n\n            </tr>\n        </tbody>\n    </table>\n    <table width=\"100%\" style=\"margin-top:-21px; font-weight:bold\">\n        <tr>\n            <td>\n                <p>Please pay in favour of \"M.D.MOHTA RAKHI PVT.LTD.\" Through either</p>\n                <p>ICICI Bank Ltd.,Kolkata A/c No 694905600912 IFSC Code ICIC0006949 or</p>\n                <p>DBS Bank India Limited A/c No 828200135528 IFSC Code DBSS0IN0828</p>\n                <p>Rakhi is exempted from GST vide Notification No.19/2018 Dated 26/07/18</p>\n            </td>\n            <td style=\"text-align:center;\">Authorised Signatory</td>\n        </tr>\n        <tr>\n            <td><p>Amendment No.02/2017 Dated 28/06/2017</p></td>\n            <td style=\"text-align:center;\">E.& O.E.</td>\n        </tr>\n    </table>\n    {% endif %}\n    {% endfor %}\n</div>\n{% endif %}",
 "idx": 0,
 "line_breaks": 0,
 "margin_bottom": 15.0,
 "margin_left": 15.0,
 "margin_right": 15.0,
 "margin_top": 15.0,
 "modified": "2025-10-16 12:02:45.439893",
 "modified_by": "Administrator",
 "module": "Shree",
 "name": "Bill of Supply - Shree",
 "owner": "Administrator",
 "page_number": "Hide",
 "pdf_generator": "wkhtmltopdf",
 "print_format_builder": 0,
 "print_format_builder_beta": 0,
 "print_format_for": "DocType",
 "print_format_type": "Jinja",
 "raw_printing": 0,
 "show_section_headings": 0,
 "standard": "Yes"
}